mcp_sdk/__init__.py
mcp_sdk/auth.py
mcp_sdk/client.py
mcp_sdk/connection_manager.py
mcp_sdk/exceptions.py
mcp_sdk/heartbeat.py
mcp_sdk/mcp_client.py
mcp_sdk/mcp_sdk.py
mcp_sdk/models.py
mcp_sdk/signature.py
mcp_sdk/websocket_adapter.py
tuya_developer_agent_mcp_sdk-0.1.0.dist-info/METADATA
tuya_developer_agent_mcp_sdk-0.1.0.dist-info/WHEEL
tuya_developer_agent_mcp_sdk-0.1.0.dist-info/top_level.txt
tuya_developer_agent_mcp_sdk-0.1.0.dist-info/RECORD
