Metadata-Version: 2.4
Name: tuya-developer-agent-mcp-sdk
Version: 0.1.0
Summary: 涂鸦智能体平台MCP接入sdk
Author-email: 言言学姐 <2769221745@qq.com>
License: MIT
Project-URL: Homepage, https://github.com/tuya
Project-URL: Repository, https://github.com/tuya/tuya-mcp-sdk
Project-URL: Documentation, https://github.com/tuya/tuya-mcp-sdk/blob/master/README.md
Classifier: Development Status :: 3 - Alpha
Classifier: Intended Audience :: Developers
Classifier: License :: OSI Approved :: MIT License
Classifier: Programming Language :: Python :: 3
Classifier: Programming Language :: Python :: 3.10
Classifier: Programming Language :: Python :: 3.11
Classifier: Programming Language :: Python :: 3.12
Classifier: Programming Language :: Python :: 3.13
Requires-Python: >=3.10
Requires-Dist: fastmcp>=0.1.0
Requires-Dist: websockets>=13.0
Requires-Dist: aiohttp>=3.12.15
Requires-Dist: aiohttp-cors>=0.7.0
Requires-Dist: pydantic>=2.10.0
Requires-Dist: cryptography>=44.0.1
Requires-Dist: asyncio-mqtt>=0.16.0
Requires-Dist: pip-system-certs>=4.0
Requires-Dist: python-socks>=2.0.0
Provides-Extra: dev
Requires-Dist: pytest>=7.0.0; extra == "dev"
Requires-Dist: pytest-asyncio>=0.21.0; extra == "dev"
Requires-Dist: black>=23.0.0; extra == "dev"
Requires-Dist: flake8>=6.0.0; extra == "dev"
Requires-Dist: mypy>=1.0.0; extra == "dev"
Requires-Dist: pytest-cov>=4.0.0; extra == "dev"
